prettysql/__init__.py
prettysql/prettysql.py
prettysql/queries/abc.txt
prettysql/queries/query.sql
prettysql-0.0.4.dist-info/METADATA
prettysql-0.0.4.dist-info/WHEEL
prettysql-0.0.4.dist-info/entry_points.txt
prettysql-0.0.4.dist-info/top_level.txt
prettysql-0.0.4.dist-info/RECORD
