Metadata-Version: 2.1
Name: prettysql
Version: 0.0.4
Summary: pretty sql
Home-page: https://github.com/iuiu34/prettysql
Author: iuiu34
Author-email: 
License: COPYRIGHT
Platform: UNKNOWN
Classifier: Development Status :: 2 - Pre-Alpha
Classifier: Programming Language :: Python :: 3 :: Only
Classifier: Programming Language :: Python :: 3.6
Requires-Dist: fire
